blacksheep/__init__.py
blacksheep/asgi.pyi
blacksheep/baseapp.c
blacksheep/baseapp.pxd
blacksheep/baseapp.py
blacksheep/baseapp.pyi
blacksheep/baseapp.pyx
blacksheep/contents.c
blacksheep/contents.pxd
blacksheep/contents.py
blacksheep/contents.pyi
blacksheep/contents.pyx
blacksheep/cookies.c
blacksheep/cookies.pxd
blacksheep/cookies.py
blacksheep/cookies.pyi
blacksheep/cookies.pyx
blacksheep/exceptions.c
blacksheep/exceptions.pxd
blacksheep/exceptions.py
blacksheep/exceptions.pyi
blacksheep/exceptions.pyx
blacksheep/headers.c
blacksheep/headers.pxd
blacksheep/headers.py
blacksheep/headers.pyi
blacksheep/headers.pyx
blacksheep/messages.c
blacksheep/messages.pxd
blacksheep/messages.py
blacksheep/messages.pyi
blacksheep/messages.pyx
blacksheep/middlewares.py
blacksheep/multipart.py
blacksheep/normalization.py
blacksheep/py.typed
blacksheep/ranges.py
blacksheep/scribe.c
blacksheep/scribe.pxd
blacksheep/scribe.py
blacksheep/scribe.pyi
blacksheep/scribe.pyx
blacksheep/url.c
blacksheep/url.pxd
blacksheep/url.py
blacksheep/url.pyi
blacksheep/url.pyx
blacksheep/client/__init__.py
blacksheep/client/connection.py
blacksheep/client/cookies.py
blacksheep/client/exceptions.py
blacksheep/client/pool.py
blacksheep/client/session.py
blacksheep/common/__init__.py
blacksheep/common/types.py
blacksheep/common/files/__init__.py
blacksheep/common/files/asyncfs.py
blacksheep/common/files/info.py
blacksheep/common/files/pathsutils.py
blacksheep/server/__init__.py
blacksheep/server/application.py
blacksheep/server/asgi.py
blacksheep/server/compression.py
blacksheep/server/controllers.py
blacksheep/server/cors.py
blacksheep/server/csrf.py
blacksheep/server/dataprotection.py
blacksheep/server/di.py
blacksheep/server/diagnostics.py
blacksheep/server/env.py
blacksheep/server/errors.py
blacksheep/server/normalization.py
blacksheep/server/process.py
blacksheep/server/redirects.py
blacksheep/server/resources.py
blacksheep/server/responses.py
blacksheep/server/routing.py
blacksheep/server/sse.py
blacksheep-2.5.1.dist-info/licenses/LICENSE
blacksheep-2.5.1.dist-info/METADATA
blacksheep-2.5.1.dist-info/WHEEL
blacksheep-2.5.1.dist-info/top_level.txt
blacksheep-2.5.1.dist-info/RECORD
