Metadata-Version: 2.4
Name: blacksheep
Version: 2.5.1
Summary: Fast web framework for Python asyncio
Author-email: Roberto Prevato <roberto.prevato@gmail.com>
License-Expression: MIT
Project-URL: Homepage, https://github.com/Neoteroi/BlackSheep
Project-URL: Documentation, https://www.neoteroi.dev/blacksheep/
Project-URL: Issues, https://github.com/Neoteroi/BlackSheep/issues
Project-URL: Repository, https://github.com/Neoteroi/BlackSheep
Project-URL: Changelog, https://github.com/Neoteroi/BlackSheep/blob/main/CHANGELOG.md
Keywords: blacksheep,web framework,asyncio
Classifier: Development Status :: 5 - Production/Stable
Classifier: Programming Language :: Python :: 3.10
Classifier: Programming Language :: Python :: 3.11
Classifier: Programming Language :: Python :: 3.12
Classifier: Programming Language :: Python :: 3.13
Classifier: Programming Language :: Python :: 3.14
Classifier: Programming Language :: Python :: Implementation :: CPython
Classifier: Programming Language :: Python :: Implementation :: PyPy
Classifier: Environment :: Web Environment
Classifier: Operating System :: OS Independent
Classifier: Framework :: AsyncIO
Classifier: Topic :: Internet :: WWW/HTTP :: HTTP Servers
Classifier: Topic :: Software Development :: Libraries :: Python Modules
Requires-Python: >=3.10
License-File: LICENSE
Requires-Dist: certifi>=2025.4.26
Requires-Dist: guardpost>=1.0.4
Requires-Dist: rodi~=2.0.8
Requires-Dist: essentials<2.0,>=1.1.8
Requires-Dist: essentials-openapi<2.0,>=1.2.0
Requires-Dist: itsdangerous~=2.2.0
Requires-Dist: h11<1.0.0,>=0.14.0
Requires-Dist: h2<5.0.0,>=4.0.0
Requires-Dist: httptools>=0.7.1; platform_python_implementation != "PyPy"
Requires-Dist: async-timeout>=4.0.0; python_version < "3.11"
Provides-Extra: jinja
Requires-Dist: Jinja2~=3.1.6; extra == "jinja"
Provides-Extra: full
Requires-Dist: cryptography<47.0.0,>=45.0.2; extra == "full"
Requires-Dist: PyJWT~=2.10.1; extra == "full"
Requires-Dist: websockets~=15.0.1; extra == "full"
Requires-Dist: Jinja2~=3.1.6; extra == "full"
Dynamic: license-file
